palisade/__init__.py
palisade/_native.cpython-310-darwin.so
palisade/_native.pyi
palisade/api.py
palisade/cli/__init__.py
palisade/cli/analyzers/__init__.py
palisade/cli/analyzers/policy_analyzer.py
palisade/cli/analyzers/threat_analyzer.py
palisade/cli/analyzers/validator_stats.py
palisade/cli/commands/__init__.py
palisade/cli/commands/policy.py
palisade/cli/commands/provenance.py
palisade/cli/commands/scan.py
palisade/cli/formatters/__init__.py
palisade/cli/formatters/rich_formatter.py
palisade/cli/formatters/sarif_formatter.py
palisade/cli/main.py
palisade/cli/models.py
palisade/cli/utils.py
palisade/core/__init__.py
palisade/core/config.py
palisade/core/constants.py
palisade/core/cosai_maturity.py
palisade/core/llm_validators.py
palisade/core/maturity_detector.py
palisade/core/maturity_levels.py
palisade/core/policy.py
palisade/core/scanner.py
palisade/core/streaming_coordinator.py
palisade/inference/__init__.py
palisade/inference/engines/__init__.py
palisade/inference/engines/base.py
palisade/inference/engines/gguf_engine.py
palisade/inference/engines/pytorch_engine.py
palisade/inference/functional_trap.py
palisade/inference/payloads/__init__.py
palisade/inference/payloads/deep_scan.py
palisade/inference/payloads/quick_scan.py
palisade/inference/payloads/tool_prompts.py
palisade/inference/perplexity_scanner.py
palisade/models/__init__.py
palisade/models/metadata.py
palisade/models/model_file.py
palisade/models/report_schema.py
palisade/models/schema_utils.py
palisade/models/types.py
palisade/models/validation_result.py
palisade/policies/cedar/default_security.cedar
palisade/policies/cedar/enhanced_security.cedar
palisade/policies/cedar/palisade.cedar
palisade/policies/cedar/permissive_development.cedar
palisade/policies/cedar/strict_production.cedar
palisade/utils/__init__.py
palisade/utils/file_security.py
palisade/utils/logging.py
palisade/utils/parallel.py
palisade/utils/patterns.py
palisade/utils/security.py
palisade/validators/__init__.py
palisade-0.1.3.dist-info/METADATA
palisade-0.1.3.dist-info/WHEEL
palisade-0.1.3.dist-info/entry_points.txt
palisade-0.1.3.dist-info/RECORD
