Metadata-Version: 2.4
Name: palisade
Version: 0.1.3
Requires-Dist: numpy>=1.19.0
Requires-Dist: psutil>=5.8.0
Requires-Dist: msgpack>=1.0.0
Requires-Dist: pydantic>=2.0.0
Requires-Dist: py-tlsh>=4.0.0
Requires-Dist: sarif-pydantic>=0.6.1
Requires-Dist: safetensors>=0.3.0
Requires-Dist: sigstore>=2.0.0
Requires-Dist: typer>=0.12.0
Requires-Dist: rich>=13.7.0
Requires-Dist: pyyaml>=6.0
Requires-Dist: torch>=2.0.0 ; extra == 'inference'
Requires-Dist: transformers>=4.35.0 ; extra == 'inference'
Requires-Dist: accelerate>=0.20.0 ; extra == 'inference'
Requires-Dist: bitsandbytes>=0.40.0 ; extra == 'inference'
Requires-Dist: llama-cpp-python>=0.2.0 ; extra == 'inference'
Requires-Dist: numpy>=1.19.0 ; extra == 'inference'
Requires-Dist: llama-cpp-python>=0.2.0 ; extra == 'inference-gguf'
Requires-Dist: torch>=2.0.0 ; extra == 'inference-pytorch'
Requires-Dist: transformers>=4.35.0 ; extra == 'inference-pytorch'
Requires-Dist: accelerate>=0.20.0 ; extra == 'inference-pytorch'
Requires-Dist: bitsandbytes>=0.40.0 ; extra == 'inference-pytorch'
Requires-Dist: numpy>=1.19.0 ; extra == 'inference-pytorch'
Provides-Extra: inference
Provides-Extra: inference-gguf
Provides-Extra: inference-pytorch
Summary: Comprehensive LLM security scanner - Palisade
Author-email: Sharath Rajasekar <sharath@highflame.com>
License: HIGHFLAME COMMERCIAL LICENSE
Requires-Python: >=3.10, <3.13
